olunicodenormalizer/__init__.py
olunicodenormalizer/base.py
olunicodenormalizer/indic.py
olunicodenormalizer/langs.py
olunicodenormalizer/normalizer.py
olunicodenormalizer-1.0.0.dist-info/LICENSE
olunicodenormalizer-1.0.0.dist-info/METADATA
olunicodenormalizer-1.0.0.dist-info/WHEEL
olunicodenormalizer-1.0.0.dist-info/top_level.txt
olunicodenormalizer-1.0.0.dist-info/RECORD
