Metadata-Version: 2.1
Name: olunicodenormalizer
Version: 1.0.0
Summary: Olchiki Unicode Normalization Toolkit
Home-page: UNKNOWN
Author: Shivnath Kisku
Author-email: 
License: MIT
Keywords: olchiki,unicode,text normalization,indic
Platform: UNKNOWN
Classifier: Development Status :: 3 - Alpha
Classifier: Intended Audience :: Education
Classifier: Operating System :: OS Independent
Classifier: License :: OSI Approved :: MIT License
Classifier: Programming Language :: Python :: 3.10
License-File: LICENSE
